ldm.py
ldm-0.1.3.dist-info/DESCRIPTION.rst
ldm-0.1.3.dist-info/METADATA
ldm-0.1.3.dist-info/RECORD
ldm-0.1.3.dist-info/WHEEL
ldm-0.1.3.dist-info/metadata.json
ldm-0.1.3.dist-info/top_level.txt
