Metadata-Version: 2.0
Name: ldm
Version: 0.1.3
Summary: get the landmars,positions,features for reconition of the face in the image
Home-page: http://www.zhaomingming.cn
Author: zhaomingming
Author-email: 13271929138@163.com
License: MIT
Platform: any
